beeper_mcp/__init__.py
beeper_mcp/server.py
chain/__init__.py
chain/beeper.py
chain/utils.py
mseep_beeper_mcp-0.1.4.dist-info/METADATA
mseep_beeper_mcp-0.1.4.dist-info/WHEEL
mseep_beeper_mcp-0.1.4.dist-info/entry_points.txt
mseep_beeper_mcp-0.1.4.dist-info/top_level.txt
mseep_beeper_mcp-0.1.4.dist-info/RECORD
